tgateway/__about__.py
tgateway/__init__.py
tgateway/__main__.py
tgateway/client.py
tgateway/constants.py
tgateway/enums.py
tgateway/exceptions.py
tgateway/integrity.py
tgateway/methods.py
tgateway/py.typed
tgateway/types.py
tgateway/cli/__init__.py
tgateway/cli/main.py
tgateway-0.1.0.dist-info/METADATA
tgateway-0.1.0.dist-info/WHEEL
tgateway-0.1.0.dist-info/entry_points.txt
tgateway-0.1.0.dist-info/licenses/LICENSE
tgateway-0.1.0.dist-info/RECORD
