Metadata-Version: 2.3
Name: tgateway
Version: 0.1.0
Summary: TGateway: the simplest way to work with a Telegram Gateway API
Project-URL: Homepage, https://tgateway.deusdeveloper.com/latest/
Project-URL: Documentation, https://tgateway.deusdeveloper.com/latest/getting-started/
Project-URL: Tracker, https://github.com/deus-developer/tgateway/issues
Project-URL: Source, https://github.com/deus-developer/tgateway
Project-URL: Telegram, https://t.me/tgateway
Author-email: Artem Ukolov <deusdeveloper@yandex.com>
License-File: LICENSE
Keywords: auth,sms,telegram,verify
Classifier: Development Status :: 4 - Beta
Classifier: Environment :: Web Environment
Classifier: Framework :: AsyncIO
Classifier: Framework :: Pydantic
Classifier: Framework :: Pydantic :: 2
Classifier: Framework :: aiohttp
Classifier: Intended Audience :: Developers
Classifier: Intended Audience :: Information Technology
Classifier: Intended Audience :: System Administrators
Classifier: License :: OSI Approved :: Apache Software License
Classifier: Operating System :: OS Independent
Classifier: Programming Language :: Python
Classifier: Programming Language :: Python :: 3
Classifier: Programming Language :: Python :: 3 :: Only
Classifier: Programming Language :: Python :: 3.9
Classifier: Programming Language :: Python :: 3.10
Classifier: Programming Language :: Python :: 3.11
Classifier: Programming Language :: Python :: 3.12
Classifier: Programming Language :: Python :: 3.13
Classifier: Programming Language :: Python :: 3.14
Classifier: Programming Language :: Python :: Implementation :: CPython
Classifier: Programming Language :: Python :: Implementation :: PyPy
Classifier: Topic :: Software Development
Classifier: Topic :: Software Development :: Libraries
Classifier: Topic :: Software Development :: Libraries :: Python Modules
Classifier: Typing :: Typed
Requires-Python: >=3.9
Requires-Dist: aiohttp>=3.7.0
Requires-Dist: pydantic>=2.0
Provides-Extra: cli
Requires-Dist: typer>=0.7.0; extra == 'cli'
Provides-Extra: dev
Requires-Dist: bandit==1.7.10; extra == 'dev'
Requires-Dist: codespell==2.3.0; extra == 'dev'
Requires-Dist: mypy==1.11.2; extra == 'dev'
Requires-Dist: pre-commit==4.0.0; extra == 'dev'
Requires-Dist: ruff==0.6.9; extra == 'dev'
Requires-Dist: semgrep==1.90.0; extra == 'dev'
Requires-Dist: typer>=0.7.0; extra == 'dev'
Provides-Extra: lint
Requires-Dist: bandit==1.7.10; extra == 'lint'
Requires-Dist: codespell==2.3.0; extra == 'lint'
Requires-Dist: mypy==1.11.2; extra == 'lint'
Requires-Dist: ruff==0.6.9; extra == 'lint'
Requires-Dist: semgrep==1.90.0; extra == 'lint'
Requires-Dist: typer>=0.7.0; extra == 'lint'
Provides-Extra: optionals
Requires-Dist: typer>=0.7.0; extra == 'optionals'
Provides-Extra: types
Requires-Dist: mypy==1.11.2; extra == 'types'
Requires-Dist: typer>=0.7.0; extra == 'types'
